restricted_partition/__init__.py
restricted_partition/py.typed
restricted_partition/README.md
restricted_partition-0.1.1.dist-info/METADATA
restricted_partition-0.1.1.dist-info/WHEEL
restricted_partition-0.1.1.dist-info/RECORD
