Metadata-Version: 2.1
Name: restricted-partition
Version: 0.1.1
Summary: Integer partitions with an optional max length
License: MIT
Author: Shay Hill
Author-email: shay_public@hotmail.com
Requires-Python: >=3.9,<4.0
Classifier: License :: OSI Approved :: MIT License
Classifier: Programming Language :: Python :: 3
Classifier: Programming Language :: Python :: 3.9
Classifier: Programming Language :: Python :: 3.10
Classifier: Programming Language :: Python :: 3.11
